pkg_init/__init__.py
pkg_init/core.py
pkg_init/project/.gitignore
pkg_init/project/MANIFEST.in
pkg_init/project/Makefile
pkg_init/project/setup.py
pkg_init/project/project/__init__.py
pkg_init/project/project/utils/__init__.py
pkg_init/project/project/utils/version.py
pkg_init/project/tests/__init__.py
pkg_init/project/tests/alltest.py
pkg_init/utils/version.py
pkg_init-1.0.1.dist-info/METADATA
pkg_init-1.0.1.dist-info/RECORD
pkg_init-1.0.1.dist-info/WHEEL
pkg_init-1.0.1.dist-info/entry_points.txt
pkg_init-1.0.1.dist-info/top_level.txt
tests/__init__.py
tests/versiontest.py
