Metadata-Version: 2.1
Name: pkg-init
Version: 1.0.1
Summary: Initialize on a new package.
Home-page: https://github.com/bluelief/pkg-init
Author: bluelief
Author-email: UNKNOWN
License: MIT
Project-URL: Github, https://github.com/bluelief/pkg-init
Keywords: python,project
Platform: UNKNOWN
Classifier: Development Status :: 3 - Alpha
Classifier: Programming Language :: Python :: 3
Classifier: License :: OSI Approved :: MIT License
Classifier: Natural Language :: Japanese
